LICENSE
README.md
setup.py
execution_time_wrapper/__init__.py
execution_time_wrapper/_version.py
execution_time_wrapper/log_based.py
execution_time_wrapper/print_based.py
execution_time_wrapper.egg-info/PKG-INFO
execution_time_wrapper.egg-info/SOURCES.txt
execution_time_wrapper.egg-info/dependency_links.txt
execution_time_wrapper.egg-info/top_level.txt