Metadata-Version: 2.1
Name: execution-time-wrapper
Version: 1.0.1
Summary: A Python package with some simple wrapper functions to print the execution time of methods
Home-page: https://github.com/LeonardoAlchieri/ExecutionTimeWrapper
Author: Leonardo Alchieri
Author-email: leonardo@alchieri.eu
License: MIT
Keywords: time,wrapper,log,print,execution,speed
Classifier: Programming Language :: Python
Classifier: Programming Language :: Python :: 3.6
Classifier: Programming Language :: Python :: 3.7
Classifier: Programming Language :: Python :: 3.8
Classifier: Programming Language :: Python :: 3.9
Classifier: Programming Language :: Python :: 3 :: Only
Classifier: Development Status :: 5 - Production/Stable
Classifier: Environment :: Console
Classifier: Intended Audience :: Developers
Classifier: License :: OSI Approved :: MIT License
Requires-Python: >=3.6
License-File: LICENSE
